proto/ast_pb2.py
proto/ast_pb2.pyi
proto/ast_pb2_grpc.py
proto/ast_pb2_grpc.pyi
proto/messages_pb2.py
proto/messages_pb2.pyi
proto/messages_pb2_grpc.py
proto/messages_pb2_grpc.pyi
rappel/__init__.py
rappel/actions.py
rappel/bridge.py
rappel/dependencies.py
rappel/exceptions.py
rappel/formatter.py
rappel/ir_builder.py
rappel/logger.py
rappel/registry.py
rappel/schedule.py
rappel/serialization.py
rappel/worker.py
rappel/workflow.py
rappel/workflow_runtime.py
rappel/bin/boot-rappel-singleton
rappel/bin/rappel-bridge
rappel/bin/start-workers
rappel-0.7.2.dist-info/METADATA
rappel-0.7.2.dist-info/entry_points.txt
rappel-0.7.2.dist-info/RECORD
rappel-0.7.2.data/scripts/rappel-bridge
rappel-0.7.2.data/scripts/boot-rappel-singleton
rappel-0.7.2.data/scripts/start-workers
rappel-0.7.2.dist-info/WHEEL
