Metadata-Version: 2.4
Name: rappel
Version: 0.7.2
Summary: Distributed & durable background events in Python
Requires-Python: >=3.10
Requires-Dist: googleapis-common-protos>=1.72.0
Requires-Dist: grpcio<2,>=1.66
Requires-Dist: protobuf<6,>=5.29
Requires-Dist: pydantic<3,>=2
Provides-Extra: dev
Requires-Dist: pytest>=8; extra == 'dev'
